{
  "name": "main",
  "version": "0.0.0",
  "description": "Main App",
  "dependencies": {
    "famous/polyfills": "git+ssh://git@github.com:Famous/famous-polyfills.git#master",
    "famous/engine": "git+ssh://git@github.com:Famous/famous.git#master",
    "famous/surface": "git+ssh://git@github.com:Famous/famous.git#master",
    "famous/modifier": "git+ssh://git@github.com:Famous/famous.git#master",
    "famous/view": "git+ssh://git@github.com:Famous/famous.git#master",
    "famous/transform": "git+ssh://git@github.com:Famous/famous.git#master",
    "famous/input/touch-sync": "git+ssh://git@github.com:Famous/famous-sync.git#master",
    "famous/physics/engine": "git+ssh://git@github.com:Famous/famous-physics.git#master",
    "famous/physics/forces/drag": "git+ssh://git@github.com:Famous/famous-physics.git#master",
    "famous/transitions/transitionable": "git+ssh://git@github.com:Famous/famous-transitions.git#master",
    "famous/transitions/multiple-transition": "git+ssh://git@github.com:Famous/famous-transitions.git#master",
    "famous/transitions/tween-transition": "git+ssh://git@github.com:Famous/famous-transitions.git#master"
  },
  "scripts": ["index.js", "**/*.js"],
  "styles": ["styles.css"],
  "images": ["favicon.ico", "img/**/*.png"],
  "fonts": [],
  "templates": [],
  "files": []
}
